<xml xmlns:v="urn:schemas-microsoft-com:vml"
 xmlns:o="urn:schemas-microsoft-com:office:office"
 xmlns:p="urn:schemas-microsoft-com:office:powerpoint"
 xmlns:oa="urn:schemas-microsoft-com:office:activation">
 <o:shapelayout v:ext="edit">
  <o:idmap v:ext="edit" data="250"/>
 </o:shapelayout><p:colorscheme
  colors="#f3f6e9,#000000,#666699,#000000,#9bb0cb,#d1e0ce,#8ea642,#cccc00"/>
 <v:background id="_x0000_s256001" o:bwmode="white" fillcolor="#f3f6e9 [0]">
  <v:fill color2="#d1e0ce [5]"/>
 </v:background><p:shaperange id="_x0000_s256002">
  <v:group id="_x0000_s256002" style='position:absolute;left:130.625pt;top:126pt;
   width:538.375pt;height:252pt' coordorigin="1045,1008" coordsize="4307,2016">
   <v:oval id="_x0000_s256003" style='position:absolute;left:4392;top:1008;
    width:960;height:960;flip:x;mso-wrap-style:none;v-text-anchor:middle'
    o:bwmode="undrawn" fillcolor="#d1e0ce [5]" stroked="f" strokecolor="black [1]">
    <v:shadow color="#669 [2]"/>
    <p:tag name="___PPTMac11" type="binary" datasize="284" dataoffset="36"/>
   </v:oval><v:oval id="_x0000_s256004" style='position:absolute;left:3264;
    top:1008;width:960;height:960;flip:x;mso-wrap-style:none;v-text-anchor:middle'
    o:bwmode="undrawn" fillcolor="#d1e0ce [5]" stroked="f" strokecolor="#d1e0ce [5]">
    <v:shadow color="#669 [2]"/>
    <p:tag name="___PPTMac11" type="binary" datasize="284" dataoffset="37"/>
   </v:oval><v:oval id="_x0000_s256005" style='position:absolute;left:2136;
    top:1008;width:960;height:960;flip:x;mso-wrap-style:none;v-text-anchor:middle'
    o:bwmode="undrawn" filled="f" fillcolor="#e0e0f0" strokecolor="#d1e0ce [5]"
    strokeweight="2.25pt">
    <v:shadow color="#669 [2]"/>
    <p:tag name="___PPTMac11" type="binary" datasize="284" dataoffset="38"/>
   </v:oval><v:oval id="_x0000_s256006" style='position:absolute;left:2136;
    top:2064;width:960;height:960;flip:x;mso-wrap-style:none;v-text-anchor:middle'
    o:bwmode="undrawn" fillcolor="#d1e0ce [5]" stroked="f" strokecolor="#d1e0ce [5]"
    strokeweight="2.25pt">
    <v:shadow color="#669 [2]"/>
    <p:tag name="___PPTMac11" type="binary" datasize="284" dataoffset="39"/>
   </v:oval><v:oval id="_x0000_s256007" style='position:absolute;left:1045;
    top:2064;width:960;height:960;flip:x;mso-wrap-style:none;v-text-anchor:middle'
    o:bwmode="undrawn" fillcolor="#d1e0ce [5]" stroked="f" strokecolor="#d1e0ce [5]">
    <v:shadow color="#669 [2]"/>
    <p:tag name="___PPTMac11" type="binary" datasize="284" dataoffset="40"/>
   </v:oval><v:oval id="_x0000_s256008" style='position:absolute;left:4392;
    top:2064;width:960;height:960;flip:x;mso-wrap-style:none;v-text-anchor:middle'
    o:bwmode="undrawn" filled="f" fillcolor="#e0e0f0" strokecolor="#d1e0ce [5]"
    strokeweight="2.25pt">
    <v:shadow color="#669 [2]"/>
    <p:tag name="___PPTMac11" type="binary" datasize="284" dataoffset="41"/>
   </v:oval></v:group></p:shaperange>
 <p:shaperange id="_x0000_s256009">
  <v:shapetype id="_x0000_s256009" style='position:absolute;left:36pt;top:492pt;
   width:168pt;height:36pt' coordsize="21600,21600" o:master="" o:spt="1"
   path="m,l,21600r21600,l21600,xe" filled="f" fillcolor="#9bb0cb [4]"
   stroked="f" strokecolor="black [1]">
   <v:fill color2="#f3f6e9 [0]" o:detectmouseclick="t"/>
   <v:stroke joinstyle="miter" o:forcedash="t"/>
   <v:shadow color="#669 [2]"/>
   <v:path gradientshapeok="t" o:connecttype="rect"/>
   <o:lock v:ext="edit" grouping="t"/>
   <p:placeholder type="dateTime" position="2" size="half"/>
   <p:tag name="___PPTMac11" type="binary" datasize="284" dataoffset="42"/>
  </v:shapetype></p:shaperange>
 <p:shaperange id="_x0000_s256010">
  <v:shapetype id="_x0000_s256010" style='position:absolute;left:246pt;top:492pt;
   width:228pt;height:36pt' coordsize="21600,21600" o:master="" o:spt="1"
   path="m,l,21600r21600,l21600,xe" filled="f" fillcolor="#9bb0cb [4]"
   stroked="f" strokecolor="black [1]">
   <v:fill color2="#f3f6e9 [0]" o:detectmouseclick="t"/>
   <v:stroke joinstyle="miter" o:forcedash="t"/>
   <v:shadow color="#669 [2]"/>
   <v:path gradientshapeok="t" o:connecttype="rect"/>
   <o:lock v:ext="edit" grouping="t"/>
   <p:placeholder type="footer" position="3" size="quarter"/>
   <p:tag name="___PPTMac11" type="binary" datasize="284" dataoffset="43"/>
  </v:shapetype></p:shaperange>
 <p:shaperange id="_x0000_s256011">
  <v:shapetype id="_x0000_s256011" style='position:absolute;left:516pt;top:492pt;
   width:168pt;height:36pt' coordsize="21600,21600" o:master="" o:spt="1"
   path="m,l,21600r21600,l21600,xe" filled="f" fillcolor="#9bb0cb [4]"
   stroked="f" strokecolor="black [1]">
   <v:fill color2="#f3f6e9 [0]" o:detectmouseclick="t"/>
   <v:stroke joinstyle="miter" o:forcedash="t"/>
   <v:shadow color="#669 [2]"/>
   <v:path gradientshapeok="t" o:connecttype="rect"/>
   <o:lock v:ext="edit" grouping="t"/>
   <p:placeholder type="slideNumber" position="4" size="quarter"/>
   <p:tag name="___PPTMac11" type="binary" datasize="284" dataoffset="44"/>
  </v:shapetype></p:shaperange>
 <p:shaperange id="_x0000_m256012">
  <v:shapetype id="_x0000_m256012" style='position:absolute;left:54pt;top:96pt;
   width:612pt;height:152.25pt;v-text-anchor:bottom' coordsize="21600,21600"
   o:master="" o:spt="1" path="m,l,21600r21600,l21600,xe" filled="f"
   fillcolor="#9bb0cb [4]" stroked="f" strokecolor="black [1]">
   <v:fill color2="#f3f6e9 [0]" o:detectmouseclick="t"/>
   <v:stroke joinstyle="miter" o:forcedash="t"/>
   <v:shadow color="#669 [2]"/>
   <v:path gradientshapeok="t" o:connecttype="rect"/>
   <o:lock v:ext="edit" grouping="t"/>
   <p:placeholder type="centerTitle"/>
  </v:shapetype></p:shaperange>
 <p:shaperange id="_x0000_m256013">
  <v:shapetype id="_x0000_m256013" style='position:absolute;left:162pt;top:276pt;
   width:7in;height:138pt' coordsize="21600,21600" o:master="" o:spt="1"
   path="m,l,21600r21600,l21600,xe" filled="f" fillcolor="#9bb0cb [4]"
   stroked="f" strokecolor="black [1]">
   <v:fill color2="#f3f6e9 [0]" o:detectmouseclick="t"/>
   <v:stroke joinstyle="miter" o:forcedash="t"/>
   <v:shadow color="#669 [2]"/>
   <v:path gradientshapeok="t" o:connecttype="rect"/>
   <o:lock v:ext="edit" grouping="t"/>
   <p:placeholder type="subTitle" position="1"/>
  </v:shapetype></p:shaperange>
</xml>