<xml xmlns:o="urn:schemas-microsoft-com:office:office">
 <o:File HRef="master04.htm"/>
 <o:File HRef="master04.xml"/>
 <o:File HRef="preview.wmf"/>
 <o:File HRef="master05.htm"/>
 <o:File HRef="master05.xml"/>
 <o:File HRef="pres.xml"/>
 <o:File HRef="editdata.mso"/>
 <o:File HRef="slide0001.htm"/>
 <o:File HRef="master05_background.gif"/>
 <o:File HRef="master05_image001.gif"/>
 <o:File HRef="slide0003.htm"/>
 <o:File HRef="master04_background.gif"/>
 <o:File HRef="master04_image002.gif"/>
 <o:File HRef="slide0013.htm"/>
 <o:File HRef="slide0005.htm"/>
 <o:File HRef="slide0007.htm"/>
 <o:File HRef="slide0009.htm"/>
 <o:File HRef="slide0014.htm"/>
 <o:File HRef="slide0017.htm"/>
 <o:File HRef="slide0017_image003.gif"/>
 <o:File HRef="slide0017_image004.gif"/>
 <o:File HRef="slide0017_image005.gif"/>
 <o:File HRef="slide0017_image006.gif"/>
 <o:File HRef="slide0017_image007.gif"/>
 <o:File HRef="slide0017_image008.gif"/>
 <o:File HRef="slide0017_image009.gif"/>
 <o:File HRef="slide0017_image010.gif"/>
 <o:File HRef="slide0017_image011.gif"/>
 <o:File HRef="slide0017_image012.gif"/>
 <o:File HRef="slide0017_image013.gif"/>
 <o:File HRef="slide0008.htm"/>
 <o:File HRef="slide0008_image014.png"/>
 <o:File HRef="slide0008_image015.jpg"/>
 <o:File HRef="slide0010.htm"/>
 <o:File HRef="slide0010_image016.png"/>
 <o:File HRef="slide0010_image017.jpg"/>
 <o:File HRef="slide0011.htm"/>
 <o:File HRef="slide0011_image018.png"/>
 <o:File HRef="slide0011_image019.jpg"/>
 <o:File HRef="slide0012.htm"/>
 <o:File HRef="slide0012_image020.png"/>
 <o:File HRef="slide0012_image021.jpg"/>
 <o:File HRef="slide0019.htm"/>
 <o:File HRef="slide0019_image022.png"/>
 <o:File HRef="slide0019_image023.jpg"/>
 <o:File HRef="slide0034.htm"/>
 <o:File HRef="slide0015.htm"/>
 <o:File HRef="slide0018.htm"/>
 <o:File HRef="slide0004.htm"/>
 <o:File HRef="slide0002.htm"/>
 <o:File HRef="slide0033.htm"/>
 <o:File HRef="master01.htm"/>
 <o:File HRef="master04_stylesheet.css"/>
 <o:File HRef="script.js"/>
 <o:MainFile HRef="../hagedorn-train1105.htm"/>
 <o:File HRef="fullscreen.htm"/>
 <o:File HRef="buttons.gif"/>
 <o:File HRef="frame.htm"/>
 <o:File HRef="outline.htm"/>
 <o:File HRef="filelist.xml"/>
</xml>